hh_creator/__init__.py
hh_creator/__main__.py
hh_creator/animations.py
hh_creator/card.py
hh_creator/config.py
hh_creator/dialog.py
hh_creator/hh.py
hh_creator/main_window.py
hh_creator/player.py
hh_creator/scene.py
hh_creator/text.py
hh_creator/util.py
hh_creator/resource/Lato-Black.ttf
hh_creator/resource/default.ini
hh_creator/resource/img/seat.svg
hh_creator/resource/img/background/both.png
hh_creator/resource/img/background/left.png
hh_creator/resource/img/background/plain.png
hh_creator/resource/img/background/right.png
hh_creator/resource/img/cards/2c.svg
hh_creator/resource/img/cards/2d.svg
hh_creator/resource/img/cards/2h.svg
hh_creator/resource/img/cards/2s.svg
hh_creator/resource/img/cards/3c.svg
hh_creator/resource/img/cards/3d.svg
hh_creator/resource/img/cards/3h.svg
hh_creator/resource/img/cards/3s.svg
hh_creator/resource/img/cards/4c.svg
hh_creator/resource/img/cards/4d.svg
hh_creator/resource/img/cards/4h.svg
hh_creator/resource/img/cards/4s.svg
hh_creator/resource/img/cards/5c.svg
hh_creator/resource/img/cards/5d.svg
hh_creator/resource/img/cards/5h.svg
hh_creator/resource/img/cards/5s.svg
hh_creator/resource/img/cards/6c.svg
hh_creator/resource/img/cards/6d.svg
hh_creator/resource/img/cards/6h.svg
hh_creator/resource/img/cards/6s.svg
hh_creator/resource/img/cards/7c.svg
hh_creator/resource/img/cards/7d.svg
hh_creator/resource/img/cards/7h.svg
hh_creator/resource/img/cards/7s.svg
hh_creator/resource/img/cards/8c.svg
hh_creator/resource/img/cards/8d.svg
hh_creator/resource/img/cards/8h.svg
hh_creator/resource/img/cards/8s.svg
hh_creator/resource/img/cards/9c.svg
hh_creator/resource/img/cards/9d.svg
hh_creator/resource/img/cards/9h.svg
hh_creator/resource/img/cards/9s.svg
hh_creator/resource/img/cards/Ac.svg
hh_creator/resource/img/cards/Ad.svg
hh_creator/resource/img/cards/Ah.svg
hh_creator/resource/img/cards/As.svg
hh_creator/resource/img/cards/Jc.svg
hh_creator/resource/img/cards/Jd.svg
hh_creator/resource/img/cards/Jh.svg
hh_creator-0.2.0.dist-info/METADATA
hh_creator-0.2.0.dist-info/WHEEL
hh_creator-0.2.0.dist-info/entry_points.txt
hh_creator-0.2.0.dist-info/top_level.txt
hh_creator-0.2.0.dist-info/RECORD
