Metadata-Version: 2.4
Name: hh-creator
Version: 0.2.0
Summary: A poker hand history creator/replayer
Project-URL: Homepage, https://github.com/truenicoco/hh-creator/
Project-URL: Repository, https://github.com/truenicoco/hh-creator/
Project-URL: Issues, https://github.com/truenicoco/hh-creator/issues
Requires-Python: >=3.10
Requires-Dist: deuces>=0.2.1
Requires-Dist: poker>=0.30.0
Requires-Dist: pyqt5
Requires-Dist: pyqt5-qt5==5.15.2
